{"_via_settings":{"ui":{"annotation_editor_height":25,"annotation_editor_fontsize":0.8,"leftsidebar_width":18,"image_grid":{"img_height":80,"rshape_fill":"none","rshape_fill_opacity":0.3,"rshape_stroke":"yellow","rshape_stroke_width":2,"show_region_shape":true,"show_image_policy":"all"},"image":{"region_label":"__via_region_id__","region_color":"__via_default_region_color__","region_label_font":"10px Sans","on_image_annotation_editor_placement":"NEAR_REGION"}},"core":{"buffer_size":18,"filepath":{},"default_filepath":""},"project":{"name":"via_project_14Dec2023_11h31m"}},"_via_img_metadata":{"Image00001.jpg19071":{"filename":"Image00001.jpg","size":19071,"regions":[{"shape_attributes":{"name":"rect","x":103,"y":170,"width":85,"height":22},"region_attributes":{"name":"not_defined","type":"unknown","image_quality":{"good":true,"frontal":true,"good_illumination":true}}}],"file_attributes":{"caption":"","public_domain":"no","image_url":""}},"Image00002.jpg18126":{"filename":"Image00002.jpg","size":18126,"regions":[{"shape_attributes":{"name":"rect","x":83,"y":125,"width":117,"height":64},"region_attributes":{"name":"not_defined","type":"unknown","image_quality":{"good":true,"frontal":true,"good_illumination":true}}}],"file_attributes":{"caption":"","public_domain":"no","image_url":""}},"Image00003.jpg19280":{"filename":"Image00003.jpg","size":19280,"regions":[{"shape_attributes":{"name":"rect","x":106,"y":130,"width":52,"height":55},"region_attributes":{"name":"not_defined","type":"unknown","image_quality":{"good":true,"frontal":true,"good_illumination":true}}}],"file_attributes":{"caption":"","public_domain":"no","image_url":""}},"Image00004.jpg16951":{"filename":"Image00004.jpg","size":16951,"regions":[{"shape_attributes":{"name":"rect","x":102,"y":169,"width":48,"height":48},"region_attributes":{"name":"not_defined","type":"unknown","image_quality":{"good":true,"frontal":true,"good_illumination":true}}}],"file_attributes":{"caption":"","public_domain":"no","image_url":""}},"Image00005.jpg19576":{"filename":"Image00005.jpg","size":19576,"regions":[{"shape_attributes":{"name":"rect","x":106,"y":151,"width":41,"height":44},"region_attributes":{"name":"not_defined","type":"unknown","image_quality":{"good":true,"frontal":true,"good_illumination":true}}}],"file_attributes":{"caption":"","public_domain":"no","image_url":""}},"Image00006.jpg10156":{"filename":"Image00006.jpg","size":10156,"regions":[{"shape_attributes":{"name":"rect","x":62,"y":189,"width":26,"height":26},"region_attributes":{"name":"not_defined","type":"unknown","image_quality":{"good":true,"frontal":true,"good_illumination":true}}}],"file_attributes":{"caption":"","public_domain":"no","image_url":""}},"Image00007.jpg19828":{"filename":"Image00007.jpg","size":19828,"regions":[{"shape_attributes":{"name":"rect","x":98,"y":69,"width":55,"height":61},"region_attributes":{"name":"not_defined","type":"unknown","image_quality":{"good":true,"frontal":true,"good_illumination":true}}}],"file_attributes":{"caption":"","public_domain":"no","image_url":""}},"Image00008.jpg17021":{"filename":"Image00008.jpg","size":17021,"regions":[{"shape_attributes":{"name":"rect","x":104,"y":173,"width":45,"height":44},"region_attributes":{"name":"not_defined","type":"unknown","image_quality":{"good":true,"frontal":true,"good_illumination":true}}}],"file_attributes":{"caption":"","public_domain":"no","image_url":""}},"Image00009.jpg19046":{"filename":"Image00009.jpg","size":19046,"regions":[{"shape_attributes":{"name":"rect","x":115,"y":159,"width":39,"height":48},"region_attributes":{"name":"not_defined","type":"unknown","image_quality":{"good":true,"frontal":true,"good_illumination":true}}}],"file_attributes":{"caption":"","public_domain":"no","image_url":""}},"Image00010.jpg19072":{"filename":"Image00010.jpg","size":19072,"regions":[{"shape_attributes":{"name":"rect","x":137,"y":145,"width":48,"height":44},"region_attributes":{"name":"not_defined","type":"unknown","image_quality":{"good":true,"frontal":true,"good_illumination":true}}}],"file_attributes":{"caption":"","public_domain":"no","image_url":""}},"Image00011.jpg25151":{"filename":"Image00011.jpg","size":25151,"regions":[{"shape_attributes":{"name":"rect","x":99,"y":160,"width":49,"height":54},"region_attributes":{"name":"not_defined","type":"unknown","image_quality":{"good":true,"frontal":true,"good_illumination":true}}}],"file_attributes":{"caption":"","public_domain":"no","image_url":""}},"Image00012.jpg13172":{"filename":"Image00012.jpg","size":13172,"regions":[{"shape_attributes":{"name":"rect","x":104,"y":187,"width":40,"height":40},"region_attributes":{"name":"not_defined","type":"unknown","image_quality":{"good":true,"frontal":true,"good_illumination":true}}}],"file_attributes":{"caption":"","public_domain":"no","image_url":""}},"Image00013.jpg15720":{"filename":"Image00013.jpg","size":15720,"regions":[{"shape_attributes":{"name":"rect","x":96,"y":151,"width":50,"height":43},"region_attributes":{"name":"not_defined","type":"unknown","image_quality":{"good":true,"frontal":true,"good_illumination":true}}}],"file_attributes":{"caption":"","public_domain":"no","image_url":""}},"Image00014.jpg13306":{"filename":"Image00014.jpg","size":13306,"regions":[{"shape_attributes":{"name":"rect","x":99,"y":149,"width":45,"height":47},"region_attributes":{"name":"not_defined","type":"unknown","image_quality":{"good":true,"frontal":true,"good_illumination":true}}}],"file_attributes":{"caption":"","public_domain":"no","image_url":""}},"Image00015.jpg16108":{"filename":"Image00015.jpg","size":16108,"regions":[{"shape_attributes":{"name":"rect","x":97,"y":109,"width":45,"height":37},"region_attributes":{"name":"not_defined","type":"unknown","image_quality":{"good":true,"frontal":true,"good_illumination":true}}}],"file_attributes":{"caption":"","public_domain":"no","image_url":""}},"Image00016.jpg20872":{"filename":"Image00016.jpg","size":20872,"regions":[{"shape_attributes":{"name":"rect","x":106,"y":159,"width":36,"height":35},"region_attributes":{"name":"not_defined","type":"unknown","image_quality":{"good":true,"frontal":true,"good_illumination":true}}}],"file_attributes":{"caption":"","public_domain":"no","image_url":""}},"Image00017.jpg15439":{"filename":"Image00017.jpg","size":15439,"regions":[{"shape_attributes":{"name":"rect","x":153,"y":116,"width":59,"height":44},"region_attributes":{"name":"not_defined","type":"unknown","image_quality":{"good":true,"frontal":true,"good_illumination":true}}}],"file_attributes":{"caption":"","public_domain":"no","image_url":""}},"Image00018.jpg13954":{"filename":"Image00018.jpg","size":13954,"regions":[{"shape_attributes":{"name":"rect","x":148,"y":117,"width":58,"height":64},"region_attributes":{"name":"not_defined","type":"unknown","image_quality":{"good":true,"frontal":true,"good_illumination":true}}}],"file_attributes":{"caption":"","public_domain":"no","image_url":""}},"Image00019.jpg12846":{"filename":"Image00019.jpg","size":12846,"regions":[{"shape_attributes":{"name":"rect","x":104,"y":112,"width":50,"height":49},"region_attributes":{"name":"not_defined","type":"unknown","image_quality":{"good":true,"frontal":true,"good_illumination":true}}}],"file_attributes":{"caption":"","public_domain":"no","image_url":""}},"Image00020.jpg13242":{"filename":"Image00020.jpg","size":13242,"regions":[{"shape_attributes":{"name":"rect","x":96,"y":81,"width":39,"height":44},"region_attributes":{"name":"not_defined","type":"unknown","image_quality":{"good":true,"frontal":true,"good_illumination":true}}}],"file_attributes":{"caption":"","public_domain":"no","image_url":""}},"Image00021.jpg13608":{"filename":"Image00021.jpg","size":13608,"regions":[{"shape_attributes":{"name":"rect","x":70,"y":79,"width":47,"height":48},"region_attributes":{"name":"not_defined","type":"unknown","image_quality":{"good":true,"frontal":true,"good_illumination":true}}}],"file_attributes":{"caption":"","public_domain":"no","image_url":""}},"Image00022.jpg11139":{"filename":"Image00022.jpg","size":11139,"regions":[{"shape_attributes":{"name":"rect","x":66,"y":96,"width":56,"height":51},"region_attributes":{"name":"not_defined","type":"unknown","image_quality":{"good":true,"frontal":true,"good_illumination":true}}}],"file_attributes":{"caption":"","public_domain":"no","image_url":""}},"Image00023.jpg13458":{"filename":"Image00023.jpg","size":13458,"regions":[{"shape_attributes":{"name":"rect","x":64,"y":109,"width":50,"height":46},"region_attributes":{"name":"not_defined","type":"unknown","image_quality":{"good":true,"frontal":true,"good_illumination":true}}}],"file_attributes":{"caption":"","public_domain":"no","image_url":""}},"Image00024.jpg10049":{"filename":"Image00024.jpg","size":10049,"regions":[{"shape_attributes":{"name":"rect","x":89,"y":201,"width":53,"height":53},"region_attributes":{"name":"not_defined","type":"unknown","image_quality":{"good":true,"frontal":true,"good_illumination":true}}}],"file_attributes":{"caption":"","public_domain":"no","image_url":""}},"Image00025.jpg7842":{"filename":"Image00025.jpg","size":7842,"regions":[{"shape_attributes":{"name":"rect","x":93,"y":200,"width":47,"height":43},"region_attributes":{"name":"not_defined","type":"unknown","image_quality":{"good":true,"frontal":true,"good_illumination":true}}}],"file_attributes":{"caption":"","public_domain":"no","image_url":""}},"Image00026.jpg11070":{"filename":"Image00026.jpg","size":11070,"regions":[{"shape_attributes":{"name":"rect","x":140,"y":120,"width":48,"height":59},"region_attributes":{"name":"not_defined","type":"unknown","image_quality":{"good":true,"frontal":true,"good_illumination":true}}}],"file_attributes":{"caption":"","public_domain":"no","image_url":""}},"Image00027.jpg10116":{"filename":"Image00027.jpg","size":10116,"regions":[{"shape_attributes":{"name":"rect","x":146,"y":126,"width":43,"height":67},"region_attributes":{"name":"not_defined","type":"unknown","image_quality":{"good":true,"frontal":true,"good_illumination":true}}}],"file_attributes":{"caption":"","public_domain":"no","image_url":""}},"Image00028.jpg18475":{"filename":"Image00028.jpg","size":18475,"regions":[{"shape_attributes":{"name":"rect","x":97,"y":146,"width":75,"height":79},"region_attributes":{"name":"not_defined","type":"unknown","image_quality":{"good":true,"frontal":true,"good_illumination":true}}}],"file_attributes":{"caption":"","public_domain":"no","image_url":""}},"Image00029.jpg14869":{"filename":"Image00029.jpg","size":14869,"regions":[{"shape_attributes":{"name":"rect","x":104,"y":142,"width":74,"height":70},"region_attributes":{"name":"not_defined","type":"unknown","image_quality":{"good":true,"frontal":true,"good_illumination":true}}}],"file_attributes":{"caption":"","public_domain":"no","image_url":""}},"Image00030.jpg12263":{"filename":"Image00030.jpg","size":12263,"regions":[{"shape_attributes":{"name":"rect","x":150,"y":90,"width":53,"height":84},"region_attributes":{"name":"not_defined","type":"unknown","image_quality":{"good":true,"frontal":true,"good_illumination":true}}}],"file_attributes":{"caption":"","public_domain":"no","image_url":""}},"Image00031.jpg10533":{"filename":"Image00031.jpg","size":10533,"regions":[{"shape_attributes":{"name":"rect","x":147,"y":115,"width":43,"height":74},"region_attributes":{"name":"not_defined","type":"unknown","image_quality":{"good":true,"frontal":true,"good_illumination":true}}}],"file_attributes":{"caption":"","public_domain":"no","image_url":""}},"Image00032.jpg10351":{"filename":"Image00032.jpg","size":10351,"regions":[{"shape_attributes":{"name":"rect","x":112,"y":90,"width":46,"height":75},"region_attributes":{"name":"not_defined","type":"unknown","image_quality":{"good":true,"frontal":true,"good_illumination":true}}}],"file_attributes":{"caption":"","public_domain":"no","image_url":""}},"Image00033.jpg9266":{"filename":"Image00033.jpg","size":9266,"regions":[{"shape_attributes":{"name":"rect","x":103,"y":99,"width":50,"height":51},"region_attributes":{"name":"not_defined","type":"unknown","image_quality":{"good":true,"frontal":true,"good_illumination":true}}}],"file_attributes":{"caption":"","public_domain":"no","image_url":""}},"Image00034.jpg8663":{"filename":"Image00034.jpg","size":8663,"regions":[{"shape_attributes":{"name":"rect","x":119,"y":102,"width":48,"height":52},"region_attributes":{"name":"not_defined","type":"unknown","image_quality":{"good":true,"frontal":true,"good_illumination":true}}}],"file_attributes":{"caption":"","public_domain":"no","image_url":""}},"Image00035.jpg16562":{"filename":"Image00035.jpg","size":16562,"regions":[{"shape_attributes":{"name":"rect","x":85,"y":133,"width":68,"height":63},"region_attributes":{"name":"not_defined","type":"unknown","image_quality":{"good":true,"frontal":true,"good_illumination":true}}}],"file_attributes":{"caption":"","public_domain":"no","image_url":""}},"Image00036.jpg16031":{"filename":"Image00036.jpg","size":16031,"regions":[{"shape_attributes":{"name":"rect","x":106,"y":123,"width":66,"height":61},"region_attributes":{"name":"not_defined","type":"unknown","image_quality":{"good":true,"frontal":true,"good_illumination":true}}}],"file_attributes":{"caption":"","public_domain":"no","image_url":""}},"Image00037.jpg13472":{"filename":"Image00037.jpg","size":13472,"regions":[{"shape_attributes":{"name":"rect","x":110,"y":196,"width":40,"height":48},"region_attributes":{"name":"not_defined","type":"unknown","image_quality":{"good":true,"frontal":true,"good_illumination":true}}}],"file_attributes":{"caption":"","public_domain":"no","image_url":""}},"Image00038.jpg17202":{"filename":"Image00038.jpg","size":17202,"regions":[{"shape_attributes":{"name":"rect","x":89,"y":133,"width":67,"height":69},"region_attributes":{"name":"not_defined","type":"unknown","image_quality":{"good":true,"frontal":true,"good_illumination":true}}}],"file_attributes":{"caption":"","public_domain":"no","image_url":""}},"Image00039.jpg10550":{"filename":"Image00039.jpg","size":10550,"regions":[{"shape_attributes":{"name":"rect","x":118,"y":91,"width":45,"height":72},"region_attributes":{"name":"not_defined","type":"unknown","image_quality":{"good":true,"frontal":true,"good_illumination":true}}}],"file_attributes":{"caption":"","public_domain":"no","image_url":""}},"Image00040.jpg9699":{"filename":"Image00040.jpg","size":9699,"regions":[{"shape_attributes":{"name":"rect","x":94,"y":105,"width":49,"height":54},"region_attributes":{"name":"not_defined","type":"unknown","image_quality":{"good":true,"frontal":true,"good_illumination":true}}}],"file_attributes":{"caption":"","public_domain":"no","image_url":""}},"Image00041.jpg6815":{"filename":"Image00041.jpg","size":6815,"regions":[{"shape_attributes":{"name":"rect","x":90,"y":92,"width":54,"height":55},"region_attributes":{"name":"not_defined","type":"unknown","image_quality":{"good":true,"frontal":true,"good_illumination":true}}}],"file_attributes":{"caption":"","public_domain":"no","image_url":""}},"Image00042.jpg19529":{"filename":"Image00042.jpg","size":19529,"regions":[{"shape_attributes":{"name":"rect","x":100,"y":106,"width":73,"height":81},"region_attributes":{"name":"not_defined","type":"unknown","image_quality":{"good":true,"frontal":true,"good_illumination":true}}}],"file_attributes":{"caption":"","public_domain":"no","image_url":""}},"Image00043.jpg10329":{"filename":"Image00043.jpg","size":10329,"regions":[{"shape_attributes":{"name":"rect","x":89,"y":116,"width":58,"height":80},"region_attributes":{"name":"not_defined","type":"unknown","image_quality":{"good":true,"frontal":true,"good_illumination":true}}}],"file_attributes":{"caption":"","public_domain":"no","image_url":""}},"Image00044.jpg20160":{"filename":"Image00044.jpg","size":20160,"regions":[{"shape_attributes":{"name":"rect","x":88,"y":100,"width":66,"height":77},"region_attributes":{"name":"not_defined","type":"unknown","image_quality":{"good":true,"frontal":true,"good_illumination":true}}}],"file_attributes":{"caption":"","public_domain":"no","image_url":""}},"Image00045.jpg17730":{"filename":"Image00045.jpg","size":17730,"regions":[{"shape_attributes":{"name":"rect","x":68,"y":56,"width":102,"height":149},"region_attributes":{"name":"not_defined","type":"unknown","image_quality":{"good":true,"frontal":true,"good_illumination":true}}}],"file_attributes":{"caption":"","public_domain":"no","image_url":""}},"Image00046.jpg18064":{"filename":"Image00046.jpg","size":18064,"regions":[{"shape_attributes":{"name":"rect","x":73,"y":103,"width":44,"height":39},"region_attributes":{"name":"not_defined","type":"unknown","image_quality":{"good":true,"frontal":true,"good_illumination":true}}}],"file_attributes":{"caption":"","public_domain":"no","image_url":""}},"Image00047.jpg15887":{"filename":"Image00047.jpg","size":15887,"regions":[{"shape_attributes":{"name":"rect","x":103,"y":65,"width":84,"height":87},"region_attributes":{"name":"not_defined","type":"unknown","image_quality":{"good":true,"frontal":true,"good_illumination":true}}}],"file_attributes":{"caption":"","public_domain":"no","image_url":""}},"Image00048.jpg16810":{"filename":"Image00048.jpg","size":16810,"regions":[{"shape_attributes":{"name":"rect","x":75,"y":111,"width":65,"height":83},"region_attributes":{"name":"not_defined","type":"unknown","image_quality":{"good":true,"frontal":true,"good_illumination":true}}}],"file_attributes":{"caption":"","public_domain":"no","image_url":""}},"Image00049.jpg16391":{"filename":"Image00049.jpg","size":16391,"regions":[{"shape_attributes":{"name":"rect","x":73,"y":36,"width":104,"height":166},"region_attributes":{"name":"not_defined","type":"unknown","image_quality":{"good":true,"frontal":true,"good_illumination":true}}}],"file_attributes":{"caption":"","public_domain":"no","image_url":""}},"Image00050.jpg11901":{"filename":"Image00050.jpg","size":11901,"regions":[{"shape_attributes":{"name":"rect","x":67,"y":34,"width":132,"height":169},"region_attributes":{"name":"not_defined","type":"unknown","image_quality":{"good":true,"frontal":true,"good_illumination":true}}}],"file_attributes":{"caption":"","public_domain":"no","image_url":""}},"Image00051.jpg19258":{"filename":"Image00051.jpg","size":19258,"regions":[{"shape_attributes":{"name":"rect","x":99,"y":124,"width":45,"height":45},"region_attributes":{"name":"not_defined","type":"unknown","image_quality":{"good":true,"frontal":true,"good_illumination":true}}}],"file_attributes":{"caption":"","public_domain":"no","image_url":""}},"Image00052.jpg9807":{"filename":"Image00052.jpg","size":9807,"regions":[{"shape_attributes":{"name":"rect","x":97,"y":179,"width":55,"height":53},"region_attributes":{"name":"not_defined","type":"unknown","image_quality":{"good":true,"frontal":true,"good_illumination":true}}}],"file_attributes":{"caption":"","public_domain":"no","image_url":""}},"Image00053.jpg10116":{"filename":"Image00053.jpg","size":10116,"regions":[{"shape_attributes":{"name":"rect","x":102,"y":139,"width":84,"height":60},"region_attributes":{"name":"not_defined","type":"unknown","image_quality":{"good":true,"frontal":true,"good_illumination":true}}}],"file_attributes":{"caption":"","public_domain":"no","image_url":""}},"Image00054.jpg10080":{"filename":"Image00054.jpg","size":10080,"regions":[{"shape_attributes":{"name":"rect","x":109,"y":87,"width":46,"height":74},"region_attributes":{"name":"not_defined","type":"unknown","image_quality":{"good":true,"frontal":true,"good_illumination":true}}}],"file_attributes":{"caption":"","public_domain":"no","image_url":""}},"Image00055.jpg13229":{"filename":"Image00055.jpg","size":13229,"regions":[{"shape_attributes":{"name":"rect","x":96,"y":90,"width":57,"height":80},"region_attributes":{"name":"not_defined","type":"unknown","image_quality":{"good":true,"frontal":true,"good_illumination":true}}}],"file_attributes":{"caption":"","public_domain":"no","image_url":""}},"Image00056.jpg11194":{"filename":"Image00056.jpg","size":11194,"regions":[{"shape_attributes":{"name":"rect","x":140,"y":189,"width":38,"height":36},"region_attributes":{"name":"not_defined","type":"unknown","image_quality":{"good":true,"frontal":true,"good_illumination":true}}}],"file_attributes":{"caption":"","public_domain":"no","image_url":""}},"Image00057.jpg11453":{"filename":"Image00057.jpg","size":11453,"regions":[{"shape_attributes":{"name":"rect","x":87,"y":90,"width":52,"height":89},"region_attributes":{"name":"not_defined","type":"unknown","image_quality":{"good":true,"frontal":true,"good_illumination":true}}}],"file_attributes":{"caption":"","public_domain":"no","image_url":""}},"Image00058.jpg11200":{"filename":"Image00058.jpg","size":11200,"regions":[{"shape_attributes":{"name":"rect","x":108,"y":159,"width":37,"height":40},"region_attributes":{"name":"not_defined","type":"unknown","image_quality":{"good":true,"frontal":true,"good_illumination":true}}}],"file_attributes":{"caption":"","public_domain":"no","image_url":""}},"Image00059.jpg12735":{"filename":"Image00059.jpg","size":12735,"regions":[{"shape_attributes":{"name":"rect","x":109,"y":135,"width":45,"height":56},"region_attributes":{"name":"not_defined","type":"unknown","image_quality":{"good":true,"frontal":true,"good_illumination":true}}}],"file_attributes":{"caption":"","public_domain":"no","image_url":""}},"Image00060.jpg9807":{"filename":"Image00060.jpg","size":9807,"regions":[{"shape_attributes":{"name":"rect","x":88,"y":133,"width":60,"height":58},"region_attributes":{"name":"not_defined","type":"unknown","image_quality":{"good":true,"frontal":true,"good_illumination":true}}}],"file_attributes":{"caption":"","public_domain":"no","image_url":""}},"Image00061.jpg7485":{"filename":"Image00061.jpg","size":7485,"regions":[{"shape_attributes":{"name":"rect","x":105,"y":120,"width":51,"height":60},"region_attributes":{"name":"not_defined","type":"unknown","image_quality":{"good":true,"frontal":true,"good_illumination":true}}}],"file_attributes":{"caption":"","public_domain":"no","image_url":""}},"Image00062.jpg10348":{"filename":"Image00062.jpg","size":10348,"regions":[{"shape_attributes":{"name":"rect","x":112,"y":99,"width":53,"height":87},"region_attributes":{"name":"not_defined","type":"unknown","image_quality":{"good":true,"frontal":true,"good_illumination":true}}}],"file_attributes":{"caption":"","public_domain":"no","image_url":""}},"Image00063.jpg11302":{"filename":"Image00063.jpg","size":11302,"regions":[{"shape_attributes":{"name":"rect","x":96,"y":123,"width":61,"height":72},"region_attributes":{"name":"not_defined","type":"unknown","image_quality":{"good":true,"frontal":true,"good_illumination":true}}}],"file_attributes":{"caption":"","public_domain":"no","image_url":""}},"Image00064.jpg13375":{"filename":"Image00064.jpg","size":13375,"regions":[{"shape_attributes":{"name":"rect","x":112,"y":137,"width":47,"height":52},"region_attributes":{"name":"not_defined","type":"unknown","image_quality":{"good":true,"frontal":true,"good_illumination":true}}}],"file_attributes":{"caption":"","public_domain":"no","image_url":""}},"Image00065.jpg7772":{"filename":"Image00065.jpg","size":7772,"regions":[{"shape_attributes":{"name":"rect","x":107,"y":122,"width":55,"height":64},"region_attributes":{"name":"not_defined","type":"unknown","image_quality":{"good":true,"frontal":true,"good_illumination":true}}}],"file_attributes":{"caption":"","public_domain":"no","image_url":""}},"Image00066.jpg11176":{"filename":"Image00066.jpg","size":11176,"regions":[{"shape_attributes":{"name":"rect","x":108,"y":156,"width":62,"height":54},"region_attributes":{"name":"not_defined","type":"unknown","image_quality":{"good":true,"frontal":true,"good_illumination":true}}}],"file_attributes":{"caption":"","public_domain":"no","image_url":""}},"Image00067.jpg10028":{"filename":"Image00067.jpg","size":10028,"regions":[{"shape_attributes":{"name":"rect","x":106,"y":136,"width":57,"height":69},"region_attributes":{"name":"not_defined","type":"unknown","image_quality":{"good":true,"frontal":true,"good_illumination":true}}}],"file_attributes":{"caption":"","public_domain":"no","image_url":""}},"Image00068.jpg8755":{"filename":"Image00068.jpg","size":8755,"regions":[{"shape_attributes":{"name":"rect","x":106,"y":150,"width":62,"height":57},"region_attributes":{"name":"not_defined","type":"unknown","image_quality":{"good":true,"frontal":true,"good_illumination":true}}}],"file_attributes":{"caption":"","public_domain":"no","image_url":""}},"Image00069.jpg12174":{"filename":"Image00069.jpg","size":12174,"regions":[{"shape_attributes":{"name":"rect","x":105,"y":106,"width":58,"height":73},"region_attributes":{"name":"not_defined","type":"unknown","image_quality":{"good":true,"frontal":true,"good_illumination":true}}}],"file_attributes":{"caption":"","public_domain":"no","image_url":""}},"Image00070.jpg8259":{"filename":"Image00070.jpg","size":8259,"regions":[{"shape_attributes":{"name":"rect","x":107,"y":115,"width":66,"height":72},"region_attributes":{"name":"not_defined","type":"unknown","image_quality":{"good":true,"frontal":true,"good_illumination":true}}}],"file_attributes":{"caption":"","public_domain":"no","image_url":""}},"Image00071.jpg9131":{"filename":"Image00071.jpg","size":9131,"regions":[{"shape_attributes":{"name":"rect","x":93,"y":105,"width":74,"height":79},"region_attributes":{"name":"not_defined","type":"unknown","image_quality":{"good":true,"frontal":true,"good_illumination":true}}}],"file_attributes":{"caption":"","public_domain":"no","image_url":""}},"Image00072.jpg9472":{"filename":"Image00072.jpg","size":9472,"regions":[{"shape_attributes":{"name":"rect","x":98,"y":103,"width":62,"height":74},"region_attributes":{"name":"not_defined","type":"unknown","image_quality":{"good":true,"frontal":true,"good_illumination":true}}}],"file_attributes":{"caption":"","public_domain":"no","image_url":""}},"Image00073.jpg12401":{"filename":"Image00073.jpg","size":12401,"regions":[{"shape_attributes":{"name":"rect","x":155,"y":191,"width":25,"height":25},"region_attributes":{"name":"not_defined","type":"unknown","image_quality":{"good":true,"frontal":true,"good_illumination":true}}}],"file_attributes":{"caption":"","public_domain":"no","image_url":""}},"Image00074.jpg9128":{"filename":"Image00074.jpg","size":9128,"regions":[{"shape_attributes":{"name":"rect","x":145,"y":190,"width":32,"height":30},"region_attributes":{"name":"not_defined","type":"unknown","image_quality":{"good":true,"frontal":true,"good_illumination":true}}}],"file_attributes":{"caption":"","public_domain":"no","image_url":""}},"Image00075.jpg9249":{"filename":"Image00075.jpg","size":9249,"regions":[{"shape_attributes":{"name":"rect","x":154,"y":195,"width":28,"height":27},"region_attributes":{"name":"not_defined","type":"unknown","image_quality":{"good":true,"frontal":true,"good_illumination":true}}}],"file_attributes":{"caption":"","public_domain":"no","image_url":""}},"Image00076.jpg14475":{"filename":"Image00076.jpg","size":14475,"regions":[{"shape_attributes":{"name":"rect","x":155,"y":182,"width":33,"height":31},"region_attributes":{"name":"not_defined","type":"unknown","image_quality":{"good":true,"frontal":true,"good_illumination":true}}}],"file_attributes":{"caption":"","public_domain":"no","image_url":""}},"Image00077.jpg9848":{"filename":"Image00077.jpg","size":9848,"regions":[{"shape_attributes":{"name":"rect","x":162,"y":152,"width":37,"height":41},"region_attributes":{"name":"not_defined","type":"unknown","image_quality":{"good":true,"frontal":true,"good_illumination":true}}}],"file_attributes":{"caption":"","public_domain":"no","image_url":""}},"Image00078.jpg8983":{"filename":"Image00078.jpg","size":8983,"regions":[{"shape_attributes":{"name":"rect","x":105,"y":121,"width":42,"height":51},"region_attributes":{"name":"not_defined","type":"unknown","image_quality":{"good":true,"frontal":true,"good_illumination":true}}}],"file_attributes":{"caption":"","public_domain":"no","image_url":""}},"Image00079.jpg12664":{"filename":"Image00079.jpg","size":12664,"regions":[{"shape_attributes":{"name":"rect","x":140,"y":161,"width":40,"height":39},"region_attributes":{"name":"not_defined","type":"unknown","image_quality":{"good":true,"frontal":true,"good_illumination":true}}}],"file_attributes":{"caption":"","public_domain":"no","image_url":""}},"Image00080.jpg17527":{"filename":"Image00080.jpg","size":17527,"regions":[{"shape_attributes":{"name":"rect","x":120,"y":140,"width":30,"height":41},"region_attributes":{"name":"not_defined","type":"unknown","image_quality":{"good":true,"frontal":true,"good_illumination":true}}}],"file_attributes":{"caption":"","public_domain":"no","image_url":""}},"Image00081.jpg12882":{"filename":"Image00081.jpg","size":12882,"regions":[{"shape_attributes":{"name":"rect","x":98,"y":133,"width":50,"height":61},"region_attributes":{"name":"not_defined","type":"unknown","image_quality":{"good":true,"frontal":true,"good_illumination":true}}}],"file_attributes":{"caption":"","public_domain":"no","image_url":""}},"Image00082.jpg18523":{"filename":"Image00082.jpg","size":18523,"regions":[{"shape_attributes":{"name":"rect","x":107,"y":129,"width":43,"height":64},"region_attributes":{"name":"not_defined","type":"unknown","image_quality":{"good":true,"frontal":true,"good_illumination":true}}}],"file_attributes":{"caption":"","public_domain":"no","image_url":""}},"Image00083.jpg12807":{"filename":"Image00083.jpg","size":12807,"regions":[{"shape_attributes":{"name":"rect","x":73,"y":100,"width":45,"height":56},"region_attributes":{"name":"not_defined","type":"unknown","image_quality":{"good":true,"frontal":true,"good_illumination":true}}}],"file_attributes":{"caption":"","public_domain":"no","image_url":""}},"Image00084.jpg13269":{"filename":"Image00084.jpg","size":13269,"regions":[{"shape_attributes":{"name":"rect","x":90,"y":196,"width":74,"height":24},"region_attributes":{"name":"not_defined","type":"unknown","image_quality":{"good":true,"frontal":true,"good_illumination":true}}}],"file_attributes":{"caption":"","public_domain":"no","image_url":""}},"Image00085.jpg19267":{"filename":"Image00085.jpg","size":19267,"regions":[{"shape_attributes":{"name":"rect","x":81,"y":142,"width":44,"height":50},"region_attributes":{"name":"not_defined","type":"unknown","image_quality":{"good":true,"frontal":true,"good_illumination":true}}}],"file_attributes":{"caption":"","public_domain":"no","image_url":""}},"Image00086.jpg17346":{"filename":"Image00086.jpg","size":17346,"regions":[{"shape_attributes":{"name":"rect","x":98,"y":66,"width":42,"height":103},"region_attributes":{"name":"not_defined","type":"unknown","image_quality":{"good":true,"frontal":true,"good_illumination":true}}}],"file_attributes":{"caption":"","public_domain":"no","image_url":""}},"Image00087.jpg15418":{"filename":"Image00087.jpg","size":15418,"regions":[{"shape_attributes":{"name":"rect","x":96,"y":62,"width":43,"height":121},"region_attributes":{"name":"not_defined","type":"unknown","image_quality":{"good":true,"frontal":true,"good_illumination":true}}}],"file_attributes":{"caption":"","public_domain":"no","image_url":""}},"Image00088.jpg9654":{"filename":"Image00088.jpg","size":9654,"regions":[{"shape_attributes":{"name":"rect","x":107,"y":154,"width":26,"height":40},"region_attributes":{"name":"not_defined","type":"unknown","image_quality":{"good":true,"frontal":true,"good_illumination":true}}}],"file_attributes":{"caption":"","public_domain":"no","image_url":""}},"Image00089.jpg9888":{"filename":"Image00089.jpg","size":9888,"regions":[{"shape_attributes":{"name":"rect","x":115,"y":80,"width":33,"height":71},"region_attributes":{"name":"not_defined","type":"unknown","image_quality":{"good":true,"frontal":true,"good_illumination":true}}}],"file_attributes":{"caption":"","public_domain":"no","image_url":""}},"Image00090.jpg10095":{"filename":"Image00090.jpg","size":10095,"regions":[{"shape_attributes":{"name":"rect","x":109,"y":95,"width":40,"height":66},"region_attributes":{"name":"not_defined","type":"unknown","image_quality":{"good":true,"frontal":true,"good_illumination":true}}}],"file_attributes":{"caption":"","public_domain":"no","image_url":""}},"Image00091.jpg11664":{"filename":"Image00091.jpg","size":11664,"regions":[{"shape_attributes":{"name":"rect","x":126,"y":85,"width":34,"height":83},"region_attributes":{"name":"not_defined","type":"unknown","image_quality":{"good":true,"frontal":true,"good_illumination":true}}}],"file_attributes":{"caption":"","public_domain":"no","image_url":""}},"Image00092.jpg7795":{"filename":"Image00092.jpg","size":7795,"regions":[{"shape_attributes":{"name":"rect","x":98,"y":165,"width":32,"height":55},"region_attributes":{"name":"not_defined","type":"unknown","image_quality":{"good":true,"frontal":true,"good_illumination":true}}}],"file_attributes":{"caption":"","public_domain":"no","image_url":""}},"Image00093.jpg7654":{"filename":"Image00093.jpg","size":7654,"regions":[{"shape_attributes":{"name":"rect","x":111,"y":150,"width":34,"height":52},"region_attributes":{"name":"not_defined","type":"unknown","image_quality":{"good":true,"frontal":true,"good_illumination":true}}}],"file_attributes":{"caption":"","public_domain":"no","image_url":""}},"Image00094.jpg23159":{"filename":"Image00094.jpg","size":23159,"regions":[{"shape_attributes":{"name":"rect","x":104,"y":93,"width":52,"height":82},"region_attributes":{"name":"not_defined","type":"unknown","image_quality":{"good":true,"frontal":true,"good_illumination":true}}}],"file_attributes":{"caption":"","public_domain":"no","image_url":""}},"Image00095.jpg20784":{"filename":"Image00095.jpg","size":20784,"regions":[{"shape_attributes":{"name":"rect","x":125,"y":66,"width":39,"height":87},"region_attributes":{"name":"not_defined","type":"unknown","image_quality":{"good":true,"frontal":true,"good_illumination":true}}}],"file_attributes":{"caption":"","public_domain":"no","image_url":""}},"Image00096.jpg6645":{"filename":"Image00096.jpg","size":6645,"regions":[{"shape_attributes":{"name":"rect","x":114,"y":205,"width":33,"height":32},"region_attributes":{"name":"not_defined","type":"unknown","image_quality":{"good":true,"frontal":true,"good_illumination":true}}}],"file_attributes":{"caption":"","public_domain":"no","image_url":""}},"Image00097.jpg15018":{"filename":"Image00097.jpg","size":15018,"regions":[{"shape_attributes":{"name":"rect","x":110,"y":158,"width":33,"height":44},"region_attributes":{"name":"not_defined","type":"unknown","image_quality":{"good":true,"frontal":true,"good_illumination":true}}}],"file_attributes":{"caption":"","public_domain":"no","image_url":""}},"Image00098.jpg21008":{"filename":"Image00098.jpg","size":21008,"regions":[{"shape_attributes":{"name":"rect","x":110,"y":67,"width":43,"height":91},"region_attributes":{"name":"not_defined","type":"unknown","image_quality":{"good":true,"frontal":true,"good_illumination":true}}}],"file_attributes":{"caption":"","public_domain":"no","image_url":""}},"Image00099.jpg10552":{"filename":"Image00099.jpg","size":10552,"regions":[{"shape_attributes":{"name":"rect","x":118,"y":164,"width":33,"height":44},"region_attributes":{"name":"not_defined","type":"unknown","image_quality":{"good":true,"frontal":true,"good_illumination":true}}}],"file_attributes":{"caption":"","public_domain":"no","image_url":""}},"Image00100.jpg16167":{"filename":"Image00100.jpg","size":16167,"regions":[{"shape_attributes":{"name":"rect","x":115,"y":74,"width":37,"height":88},"region_attributes":{"name":"not_defined","type":"unknown","image_quality":{"good":true,"frontal":true,"good_illumination":true}}}],"file_attributes":{"caption":"","public_domain":"no","image_url":""}},"Image00101.jpg10306":{"filename":"Image00101.jpg","size":10306,"regions":[{"shape_attributes":{"name":"rect","x":94,"y":149,"width":58,"height":92},"region_attributes":{"name":"not_defined","type":"unknown","image_quality":{"good":true,"frontal":true,"good_illumination":true}}}],"file_attributes":{"caption":"","public_domain":"no","image_url":""}},"Image00102.jpg11833":{"filename":"Image00102.jpg","size":11833,"regions":[{"shape_attributes":{"name":"rect","x":98,"y":71,"width":57,"height":135},"region_attributes":{"name":"not_defined","type":"unknown","image_quality":{"good":true,"frontal":true,"good_illumination":true}}}],"file_attributes":{"caption":"","public_domain":"no","image_url":""}},"Image00103.jpg6670":{"filename":"Image00103.jpg","size":6670,"regions":[{"shape_attributes":{"name":"rect","x":112,"y":168,"width":57,"height":53},"region_attributes":{"name":"not_defined","type":"unknown","image_quality":{"good":true,"frontal":true,"good_illumination":true}}}],"file_attributes":{"caption":"","public_domain":"no","image_url":""}},"Image00104.jpg7266":{"filename":"Image00104.jpg","size":7266,"regions":[{"shape_attributes":{"name":"rect","x":126,"y":179,"width":28,"height":25},"region_attributes":{"name":"not_defined","type":"unknown","image_quality":{"good":true,"frontal":true,"good_illumination":true}}}],"file_attributes":{"caption":"","public_domain":"no","image_url":""}},"Image00105.jpg6271":{"filename":"Image00105.jpg","size":6271,"regions":[{"shape_attributes":{"name":"rect","x":127,"y":157,"width":21,"height":23},"region_attributes":{"name":"not_defined","type":"unknown","image_quality":{"good":true,"frontal":true,"good_illumination":true}}}],"file_attributes":{"caption":"","public_domain":"no","image_url":""}},"Image00106.jpg6268":{"filename":"Image00106.jpg","size":6268,"regions":[{"shape_attributes":{"name":"rect","x":129,"y":174,"width":31,"height":28},"region_attributes":{"name":"not_defined","type":"unknown","image_quality":{"good":true,"frontal":true,"good_illumination":true}}}],"file_attributes":{"caption":"","public_domain":"no","image_url":""}},"Image00107.jpg6330":{"filename":"Image00107.jpg","size":6330,"regions":[{"shape_attributes":{"name":"rect","x":108,"y":152,"width":61,"height":59},"region_attributes":{"name":"not_defined","type":"unknown","image_quality":{"good":true,"frontal":true,"good_illumination":true}}}],"file_attributes":{"caption":"","public_domain":"no","image_url":""}},"Image00108.jpg4530":{"filename":"Image00108.jpg","size":4530,"regions":[{"shape_attributes":{"name":"rect","x":115,"y":176,"width":50,"height":47},"region_attributes":{"name":"not_defined","type":"unknown","image_quality":{"good":true,"frontal":true,"good_illumination":true}}}],"file_attributes":{"caption":"","public_domain":"no","image_url":""}},"Image00109.jpg5425":{"filename":"Image00109.jpg","size":5425,"regions":[{"shape_attributes":{"name":"rect","x":114,"y":175,"width":48,"height":48},"region_attributes":{"name":"not_defined","type":"unknown","image_quality":{"good":true,"frontal":true,"good_illumination":true}}}],"file_attributes":{"caption":"","public_domain":"no","image_url":""}},"Image00110.jpg8302":{"filename":"Image00110.jpg","size":8302,"regions":[{"shape_attributes":{"name":"rect","x":122,"y":187,"width":36,"height":39},"region_attributes":{"name":"not_defined","type":"unknown","image_quality":{"good":true,"frontal":true,"good_illumination":true}}}],"file_attributes":{"caption":"","public_domain":"no","image_url":""}},"Image00111.jpg6296":{"filename":"Image00111.jpg","size":6296,"regions":[{"shape_attributes":{"name":"rect","x":109,"y":170,"width":50,"height":50},"region_attributes":{"name":"not_defined","type":"unknown","image_quality":{"good":true,"frontal":true,"good_illumination":true}}}],"file_attributes":{"caption":"","public_domain":"no","image_url":""}},"Image00112.jpg5978":{"filename":"Image00112.jpg","size":5978,"regions":[{"shape_attributes":{"name":"rect","x":125,"y":168,"width":23,"height":23},"region_attributes":{"name":"not_defined","type":"unknown","image_quality":{"good":true,"frontal":true,"good_illumination":true}}}],"file_attributes":{"caption":"","public_domain":"no","image_url":""}},"Image00113.jpg8043":{"filename":"Image00113.jpg","size":8043,"regions":[{"shape_attributes":{"name":"rect","x":110,"y":137,"width":73,"height":78},"region_attributes":{"name":"not_defined","type":"unknown","image_quality":{"good":true,"frontal":true,"good_illumination":true}}}],"file_attributes":{"caption":"","public_domain":"no","image_url":""}},"Image00114.jpg7815":{"filename":"Image00114.jpg","size":7815,"regions":[{"shape_attributes":{"name":"rect","x":112,"y":176,"width":51,"height":49},"region_attributes":{"name":"not_defined","type":"unknown","image_quality":{"good":true,"frontal":true,"good_illumination":true}}}],"file_attributes":{"caption":"","public_domain":"no","image_url":""}},"Image00115.jpg5398":{"filename":"Image00115.jpg","size":5398,"regions":[{"shape_attributes":{"name":"rect","x":128,"y":173,"width":29,"height":29},"region_attributes":{"name":"not_defined","type":"unknown","image_quality":{"good":true,"frontal":true,"good_illumination":true}}}],"file_attributes":{"caption":"","public_domain":"no","image_url":""}},"Image00116.jpg6161":{"filename":"Image00116.jpg","size":6161,"regions":[{"shape_attributes":{"name":"rect","x":129,"y":176,"width":29,"height":28},"region_attributes":{"name":"not_defined","type":"unknown","image_quality":{"good":true,"frontal":true,"good_illumination":true}}}],"file_attributes":{"caption":"","public_domain":"no","image_url":""}},"Image00117.jpg5046":{"filename":"Image00117.jpg","size":5046,"regions":[{"shape_attributes":{"name":"rect","x":135,"y":189,"width":20,"height":21},"region_attributes":{"name":"not_defined","type":"unknown","image_quality":{"good":true,"frontal":true,"good_illumination":true}}}],"file_attributes":{"caption":"","public_domain":"no","image_url":""}},"Image00118.jpg5454":{"filename":"Image00118.jpg","size":5454,"regions":[{"shape_attributes":{"name":"rect","x":130,"y":190,"width":19,"height":18},"region_attributes":{"name":"not_defined","type":"unknown","image_quality":{"good":true,"frontal":true,"good_illumination":true}}}],"file_attributes":{"caption":"","public_domain":"no","image_url":""}},"Image00119.jpg8385":{"filename":"Image00119.jpg","size":8385,"regions":[{"shape_attributes":{"name":"rect","x":128,"y":179,"width":29,"height":26},"region_attributes":{"name":"not_defined","type":"unknown","image_quality":{"good":true,"frontal":true,"good_illumination":true}}}],"file_attributes":{"caption":"","public_domain":"no","image_url":""}},"Image00120.jpg6724":{"filename":"Image00120.jpg","size":6724,"regions":[{"shape_attributes":{"name":"rect","x":132,"y":196,"width":19,"height":16},"region_attributes":{"name":"not_defined","type":"unknown","image_quality":{"good":true,"frontal":true,"good_illumination":true}}}],"file_attributes":{"caption":"","public_domain":"no","image_url":""}},"Image00121.jpg6103":{"filename":"Image00121.jpg","size":6103,"regions":[{"shape_attributes":{"name":"rect","x":112,"y":176,"width":47,"height":45},"region_attributes":{"name":"not_defined","type":"unknown","image_quality":{"good":true,"frontal":true,"good_illumination":true}}}],"file_attributes":{"caption":"","public_domain":"no","image_url":""}},"Image00122.jpg5274":{"filename":"Image00122.jpg","size":5274,"regions":[{"shape_attributes":{"name":"rect","x":127,"y":192,"width":20,"height":20},"region_attributes":{"name":"not_defined","type":"unknown","image_quality":{"good":true,"frontal":true,"good_illumination":true}}}],"file_attributes":{"caption":"","public_domain":"no","image_url":""}},"Image00123.jpg7352":{"filename":"Image00123.jpg","size":7352,"regions":[{"shape_attributes":{"name":"rect","x":112,"y":180,"width":51,"height":45},"region_attributes":{"name":"not_defined","type":"unknown","image_quality":{"good":true,"frontal":true,"good_illumination":true}}}],"file_attributes":{"caption":"","public_domain":"no","image_url":""}},"Image00124.jpg11965":{"filename":"Image00124.jpg","size":11965,"regions":[{"shape_attributes":{"name":"rect","x":111,"y":156,"width":67,"height":56},"region_attributes":{"name":"not_defined","type":"unknown","image_quality":{"good":true,"frontal":true,"good_illumination":true}}}],"file_attributes":{"caption":"","public_domain":"no","image_url":""}},"Image00125.jpg10080":{"filename":"Image00125.jpg","size":10080,"regions":[{"shape_attributes":{"name":"rect","x":110,"y":122,"width":73,"height":61},"region_attributes":{"name":"not_defined","type":"unknown","image_quality":{"good":true,"frontal":true,"good_illumination":true}}}],"file_attributes":{"caption":"","public_domain":"no","image_url":""}},"Image00126.jpg9706":{"filename":"Image00126.jpg","size":9706,"regions":[{"shape_attributes":{"name":"rect","x":82,"y":105,"width":86,"height":58},"region_attributes":{"name":"not_defined","type":"unknown","image_quality":{"good":true,"frontal":true,"good_illumination":true}}}],"file_attributes":{"caption":"","public_domain":"no","image_url":""}},"Image00127.jpg8800":{"filename":"Image00127.jpg","size":8800,"regions":[{"shape_attributes":{"name":"rect","x":110,"y":146,"width":79,"height":51},"region_attributes":{"name":"not_defined","type":"unknown","image_quality":{"good":true,"frontal":true,"good_illumination":true}}}],"file_attributes":{"caption":"","public_domain":"no","image_url":""}},"Image00128.jpg8629":{"filename":"Image00128.jpg","size":8629,"regions":[{"shape_attributes":{"name":"rect","x":105,"y":158,"width":61,"height":55},"region_attributes":{"name":"not_defined","type":"unknown","image_quality":{"good":true,"frontal":true,"good_illumination":true}}}],"file_attributes":{"caption":"","public_domain":"no","image_url":""}},"Image00129.jpg22111":{"filename":"Image00129.jpg","size":22111,"regions":[{"shape_attributes":{"name":"rect","x":82,"y":94,"width":85,"height":98},"region_attributes":{"name":"not_defined","type":"unknown","image_quality":{"good":true,"frontal":true,"good_illumination":true}}}],"file_attributes":{"caption":"","public_domain":"no","image_url":""}},"Image00130.jpg12394":{"filename":"Image00130.jpg","size":12394,"regions":[{"shape_attributes":{"name":"rect","x":72,"y":140,"width":106,"height":65},"region_attributes":{"name":"not_defined","type":"unknown","image_quality":{"good":true,"frontal":true,"good_illumination":true}}}],"file_attributes":{"caption":"","public_domain":"no","image_url":""}},"Image00131.jpg12540":{"filename":"Image00131.jpg","size":12540,"regions":[{"shape_attributes":{"name":"rect","x":118,"y":67,"width":44,"height":114},"region_attributes":{"name":"not_defined","type":"unknown","image_quality":{"good":true,"frontal":true,"good_illumination":true}}}],"file_attributes":{"caption":"","public_domain":"no","image_url":""}},"Image00132.jpg12590":{"filename":"Image00132.jpg","size":12590,"regions":[{"shape_attributes":{"name":"rect","x":56,"y":140,"width":136,"height":115},"region_attributes":{"name":"not_defined","type":"unknown","image_quality":{"good":true,"frontal":true,"good_illumination":true}}}],"file_attributes":{"caption":"","public_domain":"no","image_url":""}},"Image00133.jpg8119":{"filename":"Image00133.jpg","size":8119,"regions":[{"shape_attributes":{"name":"rect","x":71,"y":198,"width":99,"height":51},"region_attributes":{"name":"not_defined","type":"unknown","image_quality":{"good":true,"frontal":true,"good_illumination":true}}}],"file_attributes":{"caption":"","public_domain":"no","image_url":""}},"Image00134.jpg13731":{"filename":"Image00134.jpg","size":13731,"regions":[{"shape_attributes":{"name":"rect","x":85,"y":146,"width":104,"height":60},"region_attributes":{"name":"not_defined","type":"unknown","image_quality":{"good":true,"frontal":true,"good_illumination":true}}}],"file_attributes":{"caption":"","public_domain":"no","image_url":""}},"Image00135.jpg19518":{"filename":"Image00135.jpg","size":19518,"regions":[{"shape_attributes":{"name":"rect","x":98,"y":152,"width":89,"height":62},"region_attributes":{"name":"not_defined","type":"unknown","image_quality":{"good":true,"frontal":true,"good_illumination":true}}}],"file_attributes":{"caption":"","public_domain":"no","image_url":""}},"Image00136.jpg13159":{"filename":"Image00136.jpg","size":13159,"regions":[{"shape_attributes":{"name":"rect","x":84,"y":127,"width":86,"height":77},"region_attributes":{"name":"not_defined","type":"unknown","image_quality":{"good":true,"frontal":true,"good_illumination":true}}}],"file_attributes":{"caption":"","public_domain":"no","image_url":""}},"Image00137.jpg12921":{"filename":"Image00137.jpg","size":12921,"regions":[{"shape_attributes":{"name":"rect","x":97,"y":153,"width":71,"height":57},"region_attributes":{"name":"not_defined","type":"unknown","image_quality":{"good":true,"frontal":true,"good_illumination":true}}}],"file_attributes":{"caption":"","public_domain":"no","image_url":""}},"Image00138.jpg18965":{"filename":"Image00138.jpg","size":18965,"regions":[{"shape_attributes":{"name":"rect","x":103,"y":145,"width":80,"height":61},"region_attributes":{"name":"not_defined","type":"unknown","image_quality":{"good":true,"frontal":true,"good_illumination":true}}}],"file_attributes":{"caption":"","public_domain":"no","image_url":""}},"Image00139.jpg15201":{"filename":"Image00139.jpg","size":15201,"regions":[{"shape_attributes":{"name":"rect","x":97,"y":81,"width":63,"height":22},"region_attributes":{"name":"not_defined","type":"unknown","image_quality":{"good":true,"frontal":true,"good_illumination":true}}}],"file_attributes":{"caption":"","public_domain":"no","image_url":""}},"Image00140.jpg10988":{"filename":"Image00140.jpg","size":10988,"regions":[{"shape_attributes":{"name":"rect","x":102,"y":156,"width":68,"height":52},"region_attributes":{"name":"not_defined","type":"unknown","image_quality":{"good":true,"frontal":true,"good_illumination":true}}}],"file_attributes":{"caption":"","public_domain":"no","image_url":""}}},"_via_attributes":{"region":{"name":{"type":"text","description":"Name of the object","default_value":"not_defined"},"type":{"type":"dropdown","description":"Category of object","options":{"bird":"Bird","human":"Human","cup":"Cup (object)","unknown":"Unknown (object)"},"default_options":{"unknown":true}},"image_quality":{"type":"checkbox","description":"Quality of image region","options":{"blur":"Blurred region","good_illumination":"Good Illumination","frontal":"Object in Frontal View"},"default_options":{"good":true,"frontal":true,"good_illumination":true}}},"file":{"caption":{"type":"text","description":"","default_value":""},"public_domain":{"type":"radio","description":"","options":{"yes":"Yes","no":"No"},"default_options":{"no":true}},"image_url":{"type":"text","description":"","default_value":""}}},"_via_data_format_version":"2.0.10","_via_image_id_list":["Image00001.jpg19071","Image00002.jpg18126","Image00003.jpg19280","Image00004.jpg16951","Image00005.jpg19576","Image00006.jpg10156","Image00007.jpg19828","Image00008.jpg17021","Image00009.jpg19046","Image00010.jpg19072","Image00011.jpg25151","Image00012.jpg13172","Image00013.jpg15720","Image00014.jpg13306","Image00015.jpg16108","Image00016.jpg20872","Image00017.jpg15439","Image00018.jpg13954","Image00019.jpg12846","Image00020.jpg13242","Image00021.jpg13608","Image00022.jpg11139","Image00023.jpg13458","Image00024.jpg10049","Image00025.jpg7842","Image00026.jpg11070","Image00027.jpg10116","Image00028.jpg18475","Image00029.jpg14869","Image00030.jpg12263","Image00031.jpg10533","Image00032.jpg10351","Image00033.jpg9266","Image00034.jpg8663","Image00035.jpg16562","Image00036.jpg16031","Image00037.jpg13472","Image00038.jpg17202","Image00039.jpg10550","Image00040.jpg9699","Image00041.jpg6815","Image00042.jpg19529","Image00043.jpg10329","Image00044.jpg20160","Image00045.jpg17730","Image00046.jpg18064","Image00047.jpg15887","Image00048.jpg16810","Image00049.jpg16391","Image00050.jpg11901","Image00051.jpg19258","Image00052.jpg9807","Image00053.jpg10116","Image00054.jpg10080","Image00055.jpg13229","Image00056.jpg11194","Image00057.jpg11453","Image00058.jpg11200","Image00059.jpg12735","Image00060.jpg9807","Image00061.jpg7485","Image00062.jpg10348","Image00063.jpg11302","Image00064.jpg13375","Image00065.jpg7772","Image00066.jpg11176","Image00067.jpg10028","Image00068.jpg8755","Image00069.jpg12174","Image00070.jpg8259","Image00071.jpg9131","Image00072.jpg9472","Image00073.jpg12401","Image00074.jpg9128","Image00075.jpg9249","Image00076.jpg14475","Image00077.jpg9848","Image00078.jpg8983","Image00079.jpg12664","Image00080.jpg17527","Image00081.jpg12882","Image00082.jpg18523","Image00083.jpg12807","Image00084.jpg13269","Image00085.jpg19267","Image00086.jpg17346","Image00087.jpg15418","Image00088.jpg9654","Image00089.jpg9888","Image00090.jpg10095","Image00091.jpg11664","Image00092.jpg7795","Image00093.jpg7654","Image00094.jpg23159","Image00095.jpg20784","Image00096.jpg6645","Image00097.jpg15018","Image00098.jpg21008","Image00099.jpg10552","Image00100.jpg16167","Image00101.jpg10306","Image00102.jpg11833","Image00103.jpg6670","Image00104.jpg7266","Image00105.jpg6271","Image00106.jpg6268","Image00107.jpg6330","Image00108.jpg4530","Image00109.jpg5425","Image00110.jpg8302","Image00111.jpg6296","Image00112.jpg5978","Image00113.jpg8043","Image00114.jpg7815","Image00115.jpg5398","Image00116.jpg6161","Image00117.jpg5046","Image00118.jpg5454","Image00119.jpg8385","Image00120.jpg6724","Image00121.jpg6103","Image00122.jpg5274","Image00123.jpg7352","Image00124.jpg11965","Image00125.jpg10080","Image00126.jpg9706","Image00127.jpg8800","Image00128.jpg8629","Image00129.jpg22111","Image00130.jpg12394","Image00131.jpg12540","Image00132.jpg12590","Image00133.jpg8119","Image00134.jpg13731","Image00135.jpg19518","Image00136.jpg13159","Image00137.jpg12921","Image00138.jpg18965","Image00139.jpg15201","Image00140.jpg10988"]}